
  { "title" : 
    [ "London, BL, Add. 17196",
      "Digital Catalogue of Syriac Manuscripts in the British Library",
      "Selections from the Fathers",
      "Part of the third discourse of Theodotus of Ancyra against Nestorius",
      "Fragments of the treatise of Gregory Nyssen on Virginity, divided into 23 chapters.",
      "Part of the treatise of Gregory Nyssen on the Hexaemeron.",
      "Part of a discourse on the Incarnation.",
      "Notes and glosses on difficult words and phrases in the works of Gregory Nyssen and Gregory Nazianzen.",
      "ܡܢ ܗܘܦܡܢܣܛܝܩܘܢ ܕܡܐܐ ܘܚܕ ܕܠܘܬ ܩܣܪܝܐ̣. ܕܟܬܝ̈ܒ̣ܢ ܒܟ̣ܪܬ ܐܝ̈ܕܘܗܝ",
      "ܕܠܘܩܒܠ ܓܪܡܛܝܩܘܣ",
      "ܡܢ ܐܓܪܬܐ ܕܠܘܬ ܐܢܣܛܣܝܐ",
      "letter of Gregory, the father of Gregory Nazianzen",
      "ܕܓܪܝܓܪܝܘܣ ܐܒܘܗܝ ܕܬܐܠܘܓܘܣ ܡܢ ܐܓܪܬܐ ܕܟܬ݂ܒ ܠܘܬ ܐܦܝܣܩ̈ܘܦܐ܀ ܟܕ ܚܦܛܘܗܝ ܕܢܥܘܼܠ ܠܩܣܪܝܐ ܡܛܠ ܟܝܪܘܛܘܢܝܐ ܕܐܦܣܩܘܦܐ",
      "discourse ascribed to S. Peter the Apostle",
      "ܕܦܛܪܘܣ ܫܠܝܚܐ ܡܢ ܬܘܪܓܡܐ ܕܐܝܬ ܠܗ. ܡܪܬܝܢܘܬܐ ܕܠܘܬ ܕܬܚܝܬ ܪܝܫܐ܀",
      "Fragments of a manuscript of the New Testament, according to the Peshitta version.",
      "S. Luke, ch. ix. 54—ch. x. 27, ch. xii. 33—50, and ch. xiv. 26—ch. xv. 10.",
      "S. John, ch. vii. 40—ch. viii. 19, ch. ix. 30—ch. x. 9, ch. xi. 32—51, ch. xiv. 19— ch. xv. 6, ch. xv. 27—ch. xvi. 21, and ch. xix. 30—ch. xx. 3.",
      "Corinthians, ch. xii. 21 to the end.",
      "Galatians, ch. i. 1, fol. 11 b; ch. iii. 13—39.",
      "Ephesians, ch. ii. 8—ch. iii. 6.",
      "Hebrews, ch. viii. 13—ch. ix. 15." ],
    "syrTitle" : 
    [ "ܫܠ̣ܡ ܡܐܡܪܐ ܕܩܕܝܫܐ ܓܪܝܓܪܝܘܣ ܐܦܝܣܩܘܦܐ ܕܢܘܣܐ܀ ܕܥܠ ܒܬܘܠܘܬܐ ܘܙܘܘܓܐ. ܕܐܝܬ ܒܗ̣̇ ܩ̈ܦܠܐܐ ܥܣܪ̈ܝܢ ܘܬ̈ܠܬܐ܀",
      "ܡܢ ܗܘܦܡܢܣܛܝܩܘܢ ܕܡܐܐ ܘܚܕ ܕܠܘܬ ܩܣܪܝܐ̣. ܕܟܬܝ̈ܒ̣ܢ ܒܟ̣ܪܬ ܐܝ̈ܕܘܗܝ",
      "ܕܠܘܩܒܠ ܓܪܡܛܝܩܘܣ",
      "ܡܢ ܐܓܪܬܐ ܕܠܘܬ ܐܢܣܛܣܝܐ",
      "ܕܓܪܝܓܪܝܘܣ ܐܒܘܗܝ ܕܬܐܠܘܓܘܣ ܡܢ ܐܓܪܬܐ ܕܟܬ݂ܒ ܠܘܬ ܐܦܝܣܩ̈ܘܦܐ܀ ܟܕ ܚܦܛܘܗܝ ܕܢܥܘܼܠ ܠܩܣܪܝܐ ܡܛܠ ܟܝܪܘܛܘܢܝܐ ܕܐܦܣܩܘܦܐ",
      "ܕܦܛܪܘܣ ܫܠܝܚܐ ܡܢ ܬܘܪܓܡܐ ܕܐܝܬ ܠܗ. ܡܪܬܝܢܘܬܐ ܕܠܘܬ ܕܬܚܝܬ ܪܝܫܐ܀" ],
    "author" : 
    [ "Theodotus of Ancyra",
      "Gregory Nyssen" ],
    "idno" : "https:\/\/bl.syriac.uk\/ms\/852",
    "displayTitleEnglish" : "London, BL, Add. 17196Digital Catalogue of Syriac Manuscripts in the British LibrarySelections from the FathersPart of the third discourse of Theodotus of Ancyra against NestoriusFragments of the treatise of Gregory Nyssen on Virginity, divided into 23 chapters.Part of the treatise of Gregory Nyssen on the Hexaemeron.Part of a discourse on the Incarnation.Notes and glosses on difficult words and phrases in the works of Gregory Nyssen and Gregory Nazianzen.ܡܢ ܗܘܦܡܢܣܛܝܩܘܢ ܕܡܐܐ ܘܚܕ ܕܠܘܬ ܩܣܪܝܐ̣. ܕܟܬܝ̈ܒ̣ܢ ܒܟ̣ܪܬ ܐܝ̈ܕܘܗܝܕܠܘܩܒܠ ܓܪܡܛܝܩܘܣܡܢ ܐܓܪܬܐ ܕܠܘܬ ܐܢܣܛܣܝܐletter of Gregory, the father of Gregory Nazianzenܕܓܪܝܓܪܝܘܣ ܐܒܘܗܝ ܕܬܐܠܘܓܘܣ ܡܢ ܐܓܪܬܐ ܕܟܬ݂ܒ ܠܘܬ ܐܦܝܣܩ̈ܘܦܐ܀ ܟܕ ܚܦܛܘܗܝ ܕܢܥܘܼܠ ܠܩܣܪܝܐ ܡܛܠ ܟܝܪܘܛܘܢܝܐ ܕܐܦܣܩܘܦܐdiscourse ascribed to S. Peter the Apostleܕܦܛܪܘܣ ܫܠܝܚܐ ܡܢ ܬܘܪܓܡܐ ܕܐܝܬ ܠܗ. ܡܪܬܝܢܘܬܐ ܕܠܘܬ ܕܬܚܝܬ ܪܝܫܐ܀Fragments of a manuscript of the New Testament, according to the Peshitta version.S. Luke, ch. ix. 54—ch. x. 27, ch. xii. 33—50, and ch. xiv. 26—ch. xv. 10.S. John, ch. vii. 40—ch. viii. 19, ch. ix. 30—ch. x. 9, ch. xi. 32—51, ch. xiv. 19— ch. xv. 6, ch. xv. 27—ch. xvi. 21, and ch. xix. 30—ch. xx. 3.Corinthians, ch. xii. 21 to the end.Galatians, ch. i. 1, fol. 11 b; ch. iii. 13—39.Ephesians, ch. ii. 8—ch. iii. 6.Hebrews, ch. viii. 13—ch. ix. 15.",
    "persName" : 
    [ " Theodotus of Ancyra ",
      " Gregory Nyssen ",
      " Severus of Antioch " ],
    "shelfmark" : 
    [ " Add. 17,196 ",
      " BL Add MS 17196 ",
      " Add. 17,196, upper text ",
      " BL Add MS 17196, upper text ",
      " Add. 17,196, lower text ",
      " BL Add MS 17196, lower text " ],
    "finalRubrics" : 
    [ " <span lang=\"syr\" dir=\"rtl\">ܫܠ̣ܡ ܡܐܡܪܐ ܕܩܕܝܫܐ ܓܪܝܓܪܝܘܣ ܐܦܝܣܩܘܦܐ ܕܢܘܣܐ܀ ܕܥܠ ܒܬܘܠܘܬܐ ܘܙܘܘܓܐ. ܕܐܝܬ ܒܗ̣̇ ܩ̈ܦܠܐܐ ܥܣܪ̈ܝܢ ܘܬ̈ܠܬܐ܀  <\/span>" ],
    "incipits" : 
    [ "  " ],
    "script" : "syr syr-Syre",
    "material" : "perg perg",
    "classification" : 
    [ " Collected Authors " ] }